{
  "pacientes": [
    {
      "id": 1,
      "nome": "Arthur Astar",
      "cpf": "031.124.715-63"
    },
    {
      "nome": "Eder",
      "cpf": "031.124.715-63",
      "id": 2
    },
    {
      "nome": "Jonathan",
      "cpf": "031.124.715-63",
      "id": 3
    },
    {
      "id": 4,
      "nome": "Arthur Astar",
      "cpf": "031.124.715-63"
    },
    {
      "id": 5,
      "nome": "Arthur Astar",
      "cpf": "031.124.715-63"
    },
    {
      "id": 6,
      "nome": "Arthur Astar",
      "cpf": "031.124.715-63"
    },
    {
      "id": 7,
      "nome": "Arthur Astar",
      "cpf": "031.124.715-63"
    },
    {
      "id": 8,
      "nome": "Arthur Astar",
      "cpf": "031.124.715-63"
    },
    {
      "id": 9,
      "nome": "Arthur Astar",
      "cpf": "031.124.715-63"
    },
    {
      "id": 10,
      "nome": "Leidy",
      "cpf": "031.124.715-63"
    }
  ]
}
